steth/__init__.py
steth/agent/__init__.py
steth/agent/agent.py
steth/agent/api.py
steth/agent/common/__init__.py
steth/agent/common/constants.py
steth/agent/common/log.py
steth/agent/common/resource.py
steth/agent/common/utils.py
steth/agent/drivers/__init__.py
steth/agent/drivers/iperf.py
steth/agent/drivers/pcap_driver.py
steth/agent/drivers/scapy_driver.py
steth/common/__init__.py
steth/stethclient/__init__.py
steth/stethclient/agent_api.py
steth/stethclient/constants.py
steth/stethclient/shell.py
steth/stethclient/utils.py
steth/stethclient/clients/__init__.py
steth/stethclient/clients/neutron.py
steth/stethclient/drivers/__init__.py
steth/stethclient/drivers/dhcp.py
steth/stethclient/drivers/iperf_api.py
steth/tests/__init__.py
steth/tests/unit/__init__.py
steth/tests/unit/agent/__init__.py
steth/tests/unit/agent/test_agent.py
steth/tests/unit/agent/test_api.py
steth/tests/unit/agent/common/__init__.py
steth/tests/unit/agent/common/test_utils.py
steth/tests/unit/agent/drivers/__init__.py
steth/tests/unit/agent/drivers/test_iperf.py
steth/tests/unit/agent/drivers/test_pcap.py
steth/tests/unit/agent/drivers/test_scapy.py
steth/tests/unit/common/__init__.py
steth/tests/unit/stethclient/__init__.py
steth/tests/unit/stethclient/test_stethclient.py
steth-0.2.4.dist-info/DESCRIPTION.rst
steth-0.2.4.dist-info/METADATA
steth-0.2.4.dist-info/RECORD
steth-0.2.4.dist-info/WHEEL
steth-0.2.4.dist-info/entry_points.txt
steth-0.2.4.dist-info/metadata.json
steth-0.2.4.dist-info/pbr.json
steth-0.2.4.dist-info/top_level.txt
