Metadata-Version: 2.0
Name: steth
Version: 0.2.4
Summary: Steth is a sophisticated debug bridge for OpenStack Neutron.
Home-page: https://www.ustack.com/
Author: "UnitedStackSDN"
Author-email: unitedstack-sdn@googlegroups.com
License: UNKNOWN
Platform: UNKNOWN
Classifier: Environment :: OpenStack
Classifier: Intended Audience :: Information Technology
Classifier: Intended Audience :: System Administrators
Classifier: License :: OSI Approved :: Apache Software License
Classifier: Operating System :: POSIX :: Linux
Classifier: Programming Language :: Python
Classifier: Programming Language :: Python :: 2
Classifier: Programming Language :: Python :: 2.7
Classifier: Programming Language :: Python :: 2.6
Requires-Dist: cliff
Requires-Dist: jsonrpclib
Requires-Dist: netaddr
Requires-Dist: oslo.config (>=1.6.0)
Requires-Dist: pbr
Requires-Dist: pypcap
Requires-Dist: scapy (>=2.3.1)
